<atlassian-ide-plugin>
  <project-configuration>
    <servers>
      <bamboo>
        <server-id>701d0d73-da21-4dba-a1c7-031bbbbab051</server-id>
        <name>Gdansk</name>
        <url>https://gdansk.bamboo2.atlassian.com</url>
        <shared>false</shared>
        <use-favourites>false</use-favourites>
        <bamboo2>true</bamboo2>
        <plans>
          <plan key="ACC-CS" grouped="0" />
          <plan key="ACC-DPL" grouped="0" />
          <plan key="ACC-TST" grouped="0" />
          <plan key="INT-CS" grouped="0" />
          <plan key="INT-DPL" grouped="0" />
          <plan key="INT-TST" grouped="0" />
        </plans>
      </bamboo>
      <jira>
        <server-id>d252b3f6-774b-4f97-a53f-f6f7bedb4bc1</server-id>
        <name>vBox</name>
        <url>http://192.168.157.158:8080</url>
        <shared>false</shared>
      </jira>
      <jira>
        <server-id>5570b7e8-e71b-41da-88ca-95a267870ff3</server-id>
        <name>Studio</name>
        <url>https://studio.atlassian.com</url>
        <shared>false</shared>
      </jira>
    </servers>
  </project-configuration>
</atlassian-ide-plugin>